cohesity_management_sdk
tests
