Metadata-Version: 2.1
Name: cohesity-management-sdk
Version: 1.12.5
Summary: This SDK provides operations for interfacing with the Cohesity Cluster.
Home-page: https://github.com/cohesity/management-sdk-python
Author: Cohesity Inc.
Author-email: support@cohesity.com
License: UNKNOWN
Platform: UNKNOWN
License-File: LICENSE
